caffeinated/__init__.py
caffeinated/__main__.py
caffeinated/cli.py
caffeinated-0.1.1.dist-info/LICENSE
caffeinated-0.1.1.dist-info/METADATA
caffeinated-0.1.1.dist-info/WHEEL
caffeinated-0.1.1.dist-info/entry_points.txt
caffeinated-0.1.1.dist-info/top_level.txt
caffeinated-0.1.1.dist-info/RECORD
