Metadata-Version: 2.1
Name: caffeinated
Version: 0.1.1
Summary: Provide statistics about your caffeine level specifically when you'd be going to bed.
Author: Stephen Turner
License: GPL-3.0-or-later
Project-URL: Homepage, https://github.com/stephenturner/caffeinated
Project-URL: Changelog, https://github.com/stephenturner/caffeinated/releases
Project-URL: Issues, https://github.com/stephenturner/caffeinated/issues
Project-URL: CI, https://github.com/stephenturner/caffeinated/actions
Classifier: License :: OSI Approved :: GNU General Public License v3 (GPLv3)
Requires-Python: >=3.8
License-File: LICENSE
Requires-Dist: click
Provides-Extra: test
Requires-Dist: pytest; extra == "test"
